MANIFEST.in
README.md
setup.py
fabrik/__init__.py
fabrik/api.py
fabrik/hooks.py
fabrik/logger.py
fabrik/paths.py
fabrik.egg-info/PKG-INFO
fabrik.egg-info/SOURCES.txt
fabrik.egg-info/dependency_links.txt
fabrik.egg-info/entry_points.txt
fabrik.egg-info/not-zip-safe
fabrik.egg-info/requires.txt
fabrik.egg-info/top_level.txt
fabrik/cli/__init__.py
fabrik/cli/generator.py
fabrik/cli/utils.py
fabrik/cli/scripts/__init__.py
fabrik/cli/scripts/cleanup.py
fabrik/cli/scripts/init.py
fabrik/cli/templates/fabfile.py.txt
fabrik/cli/templates/fabricrc.txt
fabrik/cli/templates/index.py.txt
fabrik/cli/templates/stage.py.txt
fabrik/ext/__init__.py
fabrik/ext/celeryd.py
fabrik/ext/composer.py
fabrik/ext/envfile.py
fabrik/ext/forever.py
fabrik/ext/gunicorn.py
fabrik/ext/mysql.py
fabrik/ext/nginx.py
fabrik/ext/npm.py
fabrik/ext/postgres.py
fabrik/ext/uwsgi.py
fabrik/ext/virtualenv.py
fabrik/ext/wpcli.py
fabrik/recipes/__init__.py
fabrik/recipes/django.py
fabrik/recipes/django_uwsgi.py
fabrik/recipes/django_uwsgi_emperor.py
fabrik/recipes/node.py
fabrik/recipes/node_forever.py
fabrik/recipes/wordpress.py
fabrik/recipes/wordpress_bedrock.py
fabrik/recipes/wordpress_composer.py
fabrik/scripts/__init__.py
fabrik/scripts/fabrik.py
fabrik/transfer/__init__.py
fabrik/transfer/git.py
fabrik/transfer/scp.py
fabrik/utils/__init__.py
fabrik/utils/elocal.py
fabrik/utils/erun.py
fabrik/utils/gitext.py
requirements/dev.txt
requirements/install.txt
requirements/tests.txt